fesslix-0.5.13.dist-info/RECORD
fesslix-0.5.13.dist-info/WHEEL
fesslix-0.5.13.dist-info/METADATA
fesslix-0.5.13.dist-info/licenses/LICENSE
fesslix/gpr.cpython-313-darwin.so
fesslix/model_templates.py
fesslix/gausspoints.dat
fesslix/plot.py
fesslix/core.cpython-313-darwin.so
fesslix/ra_form.py
fesslix/tools.py
fesslix/__init__.py
fesslix/libflxlib.dylib
