Metadata-Version: 2.1
Name: fesslix
Version: 0.5.13
Summary: stochastic analysis
Author-Email: Wolfgang Betz <w.betz@fesslix.org>
Maintainer-Email: Wolfgang Betz <w.betz@fesslix.org>
License:                     GNU GENERAL PUBLIC LICENSE
Classifier: Programming Language :: Python :: 3
Classifier: Programming Language :: C++
Classifier: License :: OSI Approved :: GNU General Public License v3 (GPLv3)
Project-URL: Homepage, http://fesslix.org
Project-URL: Documentation, https://fesslix-docu.readthedocs.io/en/latest/intro.html
Project-URL: Repository, https://github.com/fesslix/fesslix.git
Project-URL: Issues, https://github.com/fesslix/fesslix/issues
Requires-Dist: pyyaml
Requires-Dist: matplotlib
Requires-Dist: numpy
Requires-Dist: scipy
